{
  "name": "The Nouneys #153",
  "description": "Meet The Nouneys, a collection of 690 unique characters from Matt Downey, paying tribute to the artists shaping CC0 culture.",
  "image": "https://nftstorage.link/ipfs/bafybeibkfmsw4v7mmmdtbrezt3gdqsuamgkcagqgumwgpdcm5hhj7mqj4a",
  "attributes": [
    {
      "key": "Eyes",
      "value": "Square Frog Green"
    },
    {
      "key": "Accessories",
      "value": "None"
    },
    {
      "key": "Head",
      "value": "Bucktooth"
    },
    {
      "key": "Body",
      "value": "Grease Slime"
    },
    {
      "key": "Background",
      "value": "Gradient"
    }
  ]
}