{
  "name": "The Nouneys #167",
  "description": "Meet The Nouneys, a collection of 690 unique characters from Matt Downey, paying tribute to the artists shaping CC0 culture.",
  "image": "https://nftstorage.link/ipfs/bafybeibfuo6rjxj2staysnmmjgy3mku2v4kbtk2i4yowijdpgzrkiy4t5i",
  "attributes": [
    {
      "key": "Eyes",
      "value": "Boney Black"
    },
    {
      "key": "Accessories",
      "value": "2 Flies"
    },
    {
      "key": "Head",
      "value": "Nouney Boney"
    },
    {
      "key": "Body",
      "value": "Bone Zone"
    },
    {
      "key": "Background",
      "value": "Chaos"
    }
  ]
}