{
  "name": "The Nouneys #60",
  "description": "Meet The Nouneys, a collection of 690 unique characters from Matt Downey, paying tribute to the artists shaping CC0 culture.",
  "image": "https://nftstorage.link/ipfs/bafybeibl77jlbaxwddgzo7tjrw4huxg45jm2qsq4z3x2p6kde6ma522lmi",
  "attributes": [
    {
      "key": "Eyes",
      "value": "Oddities Noggles"
    },
    {
      "key": "Accessories",
      "value": "Anchor Tattoo"
    },
    {
      "key": "Head",
      "value": "Goldtooth"
    },
    {
      "key": "Body",
      "value": "Alpacadabraz Lemon"
    },
    {
      "key": "Background",
      "value": "With the Light 41"
    }
  ]
}